{"Nomes":{"0":"Julius Peppers","1":"Dwight Freeney","2":"Darrelle Revis","3":"Joe Thomas","4":"Devin Hester","5":"Andre Johnson","6":"DeMarcus Ware","7":"Calvin Johnson","8":"Peyton Manning","9":"Charles Woodson","10":"Patrick Willis","11":"Troy Polamalu","12":"Champ Bailey","13":"Tony Gonzalez","14":"Ed Reed","15":"Ronde Barber","16":"Richard Seymour","17":"Steve Hutchinson","18":"Ray Lewis","19":"Randy Moss","20":"Brian Urlacher","21":"Brian Dawkins","22":"Jason Taylor","23":"LaDainian Tomlinson","24":"Alan Faneca","25":"Terrell Owens","26":"Brett Favre","27":"Isaac Bruce","28":"Edgerrin James","29":"Ty Law","30":"Kevin Mawae","31":"Kurt Warner","32":"Orlando Pace","33":"Junior Seau","34":"Zach Thomas","35":"Marvin Harrison","36":"Derrick Brooks","37":"Walter Jones","38":"Bryant Young","39":"John Lynch","40":"Morten Andersen","41":"Michael Strahan","42":"Larry Allen","43":"Jonathan Ogden","44":"Warren Sapp","45":"Will Shields","46":"Jerome Bettis","47":"Curtis Martin","48":"Willie Roaf","49":"Marshall Faulk","50":"Deion Sanders","51":"Tim Brown","52":"Aeneas Williams","53":"Jerry Rice","54":"Emmitt Smith","55":"Shannon Sharpe","56":"John Randle","57":"Bruce Smith","58":"Rod Woodson","59":"Cris Carter","60":"Darrell Green","61":"Tony Boselli","62":"LeRoy Butler","63":"Terrell Davis","64":"Randall McDaniel","65":"Bruce Matthews","66":"Andre Reed","67":"Dermontti Dawson","68":"Cortez Kennedy","69":"Thurman Thomas","70":"Troy Aikman","71":"Warren Moon","72":"Reggie White","73":"Steve Atwater","74":"Kevin Greene","75":"Charles Haley","76":"Chris Doleman","77":"Derrick Thomas","78":"Michael Irvin","79":"Dan Marino","80":"Steve Young","81":"John Elway","82":"Barry Sanders","83":"Sam Mills","84":"Richard Dent","85":"Gary Zimmerman","86":"Marcus Allen","87":"Jim Kelly","88":"Rickey Jackson","89":"Art Monk","90":"Jackie Slater","91":"Steve McMichael","92":"Ronnie Lott","93":"Joe Montana","94":"Andre Tippett","95":"James Lofton","96":"Mike Munchak","97":"Howie Long","98":"Eric Dickerson","99":"Lawrence Taylor"},"Posi\u00e7\u00e3o":{"0":"DE","1":"DE","2":"DB","3":"T","4":"PR","5":"WR","6":"LB","7":"WR","8":"QB","9":"DB","10":"LB","11":"DB","12":"DB","13":"TE","14":"DB","15":"DB","16":"DE","17":"G","18":"LB","19":"WR","20":"LB","21":"DB","22":"DE","23":"RB","24":"G","25":"WR","26":"QB","27":"WR","28":"RB","29":"DB","30":"C","31":"QB","32":"T","33":"LB","34":"LB","35":"WR","36":"LB","37":"T","38":"DT","39":"DB","40":"K","41":"DE","42":"G","43":"T","44":"DT","45":"G","46":"RB","47":"RB","48":"T","49":"RB","50":"DB","51":"WR","52":"DB","53":"WR","54":"RB","55":"TE","56":"DT","57":"DE","58":"DB","59":"WR","60":"DB","61":"T","62":"DB","63":"RB","64":"G","65":"G","66":"WR","67":"C","68":"DT","69":"RB","70":"QB","71":"QB","72":"DE","73":"DB","74":"LB","75":"DE","76":"DE","77":"LB","78":"WR","79":"QB","80":"QB","81":"QB","82":"RB","83":"LB","84":"DE","85":"T","86":"RB","87":"QB","88":"LB","89":"WR","90":"T","91":"DT","92":"DB","93":"QB","94":"LB","95":"WR","96":"G","97":"DE","98":"RB","99":"LB"},"Ano de Indu\u00e7\u00e3o":{"0":"2024","1":"2024","2":"2023","3":"2023","4":"2024","5":"2024","6":"2023","7":"2021","8":"2021","9":"2021","10":"2024","11":"2020","12":"2019","13":"2019","14":"2019","15":"2023","16":"2022","17":"2020","18":"2018","19":"2018","20":"2018","21":"2018","22":"2017","23":"2017","24":"2021","25":"2018","26":"2016","27":"2020","28":"2020","29":"2019","30":"2019","31":"2017","32":"2016","33":"2015","34":"2023","35":"2016","36":"2014","37":"2014","38":"2022","39":"2021","40":"2017","41":"2014","42":"2013","43":"2013","44":"2013","45":"2015","46":"2015","47":"2012","48":"2012","49":"2011","50":"2011","51":"2015","52":"2014","53":"2010","54":"2010","55":"2011","56":"2010","57":"2009","58":"2009","59":"2013","60":"2008","61":"2022","62":"2022","63":"2017","64":"2009","65":"2007","66":"2014","67":"2012","68":"2012","69":"2007","70":"2006","71":"2006","72":"2006","73":"2020","74":"2016","75":"2015","76":"2012","77":"2009","78":"2007","79":"2005","80":"2005","81":"2004","82":"2004","83":"2022","84":"2011","85":"2008","86":"2003","87":"2002","88":"2010","89":"2008","90":"2001","91":"2024","92":"2000","93":"2000","94":"2008","95":"2003","96":"2001","97":"2000","98":"1999","99":"1999"},"Ano Inicial":{"0":"2002","1":"2002","2":"2007","3":"2007","4":"2006","5":"2003","6":"2005","7":"2007","8":"1998","9":"1998","10":"2007","11":"2003","12":"1999","13":"1997","14":"2002","15":"1997","16":"2001","17":"2001","18":"1996","19":"1998","20":"2000","21":"1996","22":"1997","23":"2001","24":"1998","25":"1996","26":"1991","27":"1994","28":"1999","29":"1995","30":"1994","31":"1998","32":"1997","33":"1990","34":"1996","35":"1996","36":"1995","37":"1997","38":"1994","39":"1993","40":"1982","41":"1993","42":"1994","43":"1996","44":"1995","45":"1993","46":"1993","47":"1995","48":"1993","49":"1994","50":"1989","51":"1988","52":"1991","53":"1985","54":"1990","55":"1990","56":"1990","57":"1985","58":"1987","59":"1987","60":"1983","61":"1995","62":"1990","63":"1995","64":"1988","65":"1983","66":"1985","67":"1988","68":"1990","69":"1988","70":"1989","71":"1984","72":"1985","73":"1989","74":"1985","75":"1986","76":"1985","77":"1989","78":"1988","79":"1983","80":"1985","81":"1983","82":"1989","83":"1986","84":"1983","85":"1986","86":"1982","87":"1986","88":"1981","89":"1980","90":"1976","91":"1980","92":"1981","93":"1979","94":"1982","95":"1978","96":"1982","97":"1981","98":"1983","99":"1981"},"Ano Final":{"0":"2018","1":"2017","2":"2017","3":"2017","4":"2016","5":"2016","6":"2016","7":"2015","8":"2015","9":"2015","10":"2014","11":"2014","12":"2013","13":"2013","14":"2013","15":"2012","16":"2012","17":"2012","18":"2012","19":"2012","20":"2012","21":"2011","22":"2011","23":"2011","24":"2010","25":"2010","26":"2010","27":"2009","28":"2009","29":"2009","30":"2009","31":"2009","32":"2009","33":"2009","34":"2008","35":"2008","36":"2008","37":"2008","38":"2007","39":"2007","40":"2007","41":"2007","42":"2007","43":"2007","44":"2007","45":"2006","46":"2005","47":"2005","48":"2005","49":"2005","50":"2005","51":"2004","52":"2004","53":"2004","54":"2004","55":"2003","56":"2003","57":"2003","58":"2003","59":"2002","60":"2002","61":"2001","62":"2001","63":"2001","64":"2001","65":"2001","66":"2000","67":"2000","68":"2000","69":"2000","70":"2000","71":"2000","72":"2000","73":"1999","74":"1999","75":"1999","76":"1999","77":"1999","78":"1999","79":"1999","80":"1999","81":"1998","82":"1998","83":"1997","84":"1997","85":"1997","86":"1997","87":"1996","88":"1995","89":"1995","90":"1995","91":"1994","92":"1994","93":"1994","94":"1993","95":"1993","96":"1993","97":"1993","98":"1993","99":"1993"}}